puzzle_egg/Puzzle.py
puzzle_egg/__init__.py
puzzle_egg/azure_key_vault.py
puzzle_egg/main_config.py
puzzle_egg/setup.py
puzzle_egg/data/bomb-icon.png
puzzle_egg/data/kitties.txt
puzzle_egg/data/kitties2.txt
puzzle_egg/data/letter_1.png
puzzle_egg/data/letter_10.png
puzzle_egg/data/letter_2.png
puzzle_egg/data/letter_3.png
puzzle_egg/data/letter_4.png
puzzle_egg/data/letter_5.png
puzzle_egg/data/letter_6.png
puzzle_egg/data/letter_7.png
puzzle_egg/data/letter_8.png
puzzle_egg/data/letter_9.png
puzzle_egg-9.1.dist-info/METADATA
puzzle_egg-9.1.dist-info/RECORD
puzzle_egg-9.1.dist-info/WHEEL
puzzle_egg-9.1.dist-info/top_level.txt
