Metadata-Version: 2.1
Name: puzzle-egg
Version: 9.1
Summary: Puzzle for something nice
Home-page: UNKNOWN
Author: Alice Bom
Author-email: alice.bom@avanade.com
License: UNKNOWN
Keywords: puzzle,main,configuration
Platform: UNKNOWN
